persona_bench/__init__.py
persona_bench/_eval.py
persona_bench/api/README.md
persona_bench/api/__init__.py
persona_bench/api/api.py
persona_bench/api/interfaces.py
persona_bench/api/prompt_constructor.py
persona_bench/api/utils.py
persona_bench/examples/example_client.py
persona_bench/general_eval/__init__.py
persona_bench/general_eval/chain_of_thought_difference.py
persona_bench/general_eval/demographic_difference.py
persona_bench/general_eval/get_token_count.py
persona_bench/general_eval/mode_comparisons.py
persona_bench/general_eval/mode_comparisons_delta.py
persona_bench/general_eval/model_comparisons.py
persona_bench/general_eval/word_frequency_graph.py
persona_bench/main_evaluation.py
persona_bench/main_intersectionality.py
persona_bench/main_loo.py
persona_bench/main_pass_at_k.py
persona_bench/tooling/__init__.py
persona_bench/tooling/prompts.py
persona_bench/tooling/scorer.py
persona_bench/tooling/solver.py
persona_bench/tooling/utils.py
persona_bench/visualizations/__init__.py
persona_bench/visualizations/visualization_intersection.py
persona_bench/visualizations/visualization_loo.py
persona_bench/visualizations/visualization_pass_at_k.py
persona_bench-0.1.2.1.dist-info/LICENSE
persona_bench-0.1.2.1.dist-info/METADATA
persona_bench-0.1.2.1.dist-info/WHEEL
persona_bench-0.1.2.1.dist-info/RECORD
