Metadata-Version: 2.1
Name: persona-bench
Version: 0.1.2.1
Summary: Pluristic alignment evaluation benchmark for LLMs
Home-page: https://www.synthlabs.ai
License: Apache-2.0
Author: SynthLabs.ai
Author-email: team@synthlabs.ai
Requires-Python: >=3.10,<4.0
Classifier: License :: OSI Approved :: Apache Software License
Classifier: Programming Language :: Python :: 3
Classifier: Programming Language :: Python :: 3.10
Classifier: Programming Language :: Python :: 3.11
Classifier: Programming Language :: Python :: 3.12
Requires-Dist: datasets (>=2.20.0,<3.0.0)
Requires-Dist: inspect-ai (>=0.3.18,<0.4.0)
Requires-Dist: instructor (>=1.3.4,<2.0.0)
Requires-Dist: openai (>=1.36.0,<2.0.0)
Requires-Dist: pandas (>=2.2.2,<3.0.0)
Requires-Dist: pydantic (>=2.8.2,<3.0.0)
Requires-Dist: seaborn (>=0.13.2,<0.14.0)
Requires-Dist: tenacity (>=8.5.0,<9.0.0)
Project-URL: Repository, https://github.com/SynthLabsAI/PERSONA-bench
